serpent/__init__.py
serpent/__main__.py
serpent/amino.py
serpent/amino.py~
serpent/analyse.py
serpent/cli/__init__.py~
serpent/cli/__main__.py~
serpent/cli/commands/__init__.py~
serpent/cli/commands/hello.py~
serpent/codons.py~
serpent/config.py
serpent/config.py~
serpent/digit.py
serpent/dna.py
serpent/encoding.py
serpent/fasta.py
serpent/fun.py
serpent/io.py
serpent/io.py~
serpent/mathematics.py
serpent/padding.py
serpent/printing.py
serpent/stats.py
serpent/typing.py
serpent/typing.py~
serpent/visual.py
serpent/visual.py~
dna_serpent-0.2.1.dist-info/WHEEL
dna_serpent-0.2.1.dist-info/METADATA
dna_serpent-0.2.1.dist-info/licenses/LICENSE
dna_serpent-0.2.1.dist-info/RECORD
