Metadata-Version: 2.1
Name: dna-serpent
Version: 0.2.1
Summary: Serpent is an exploration into DNA sequences, codons, amino acids and genome data
License: MIT
Author-email: Peter Hillerström <peter.hillerstrom@gmail.com>
Requires-Python: >=3.8
Requires-Dist: Pillow==9.4.0
Requires-Dist: argh>=0.28.1
Requires-Dist: click>=8.1.3
Requires-Dist: matplotlib==3.7.0
Requires-Dist: more-itertools==9.0.0
Requires-Dist: numpy==1.24.2
Requires-Dist: termcolor>=2.2.0
